PythonStarterPackage-0.4.4.data/data/pythonstarterpackage/config/config.json
pythonstarterpackage/__init__.py
pythonstarterpackage/__main__.py
pythonstarterpackage/main.py
pythonstarterpackage/starterpkg.py
pythonstarterpackage/data/data.json
pythonstarterpackage/utils/__init__.py
pythonstarterpackage/utils/configloader.py
pythonstarterpackage/utils/crawler.py
pythonstarterpackage/utils/filemodder.py
PythonStarterPackage-0.4.4.dist-info/LICENSE
PythonStarterPackage-0.4.4.dist-info/METADATA
PythonStarterPackage-0.4.4.dist-info/WHEEL
PythonStarterPackage-0.4.4.dist-info/entry_points.txt
PythonStarterPackage-0.4.4.dist-info/top_level.txt
PythonStarterPackage-0.4.4.dist-info/RECORD
